gym_gathering/__init__.py
gym_gathering/envs/__init__.py
gym_gathering/envs/maze_base.py
gym_gathering/mapdata/coronary.csv
gym_gathering/mapdata/map0122.csv
gym_gathering/mapdata/map0122_small.csv
gym_gathering/mapdata/map0122_tiny.csv
gym_gathering/mapdata/map0318.csv
gym_gathering/mapdata/map0518.csv
gym_gathering/mapdata/small_vessel.csv
gym_gathering/maze_generators/__init__.py
gym_gathering/maze_generators/maze_generator.py
gym_gathering/maze_generators/rrt_generator.py
gym_gathering/observations/__init__.py
gym_gathering/observations/base_observation_generator.py
gym_gathering/observations/basic_generators.py
gym_gathering/observations/real_world.py
gym_gathering/rewards/__init__.py
gym_gathering/rewards/base_reward_generator.py
gym_gathering/rewards/episode_ends.py
gym_gathering/rewards/reward_generators.py
gym_gathering/rewards/rewards.py
gym_gathering/steps/__init__.py
gym_gathering/steps/base_step_modifier.py
gym_gathering/steps/basic_modifiers.py
gym_gathering/steps/physical_modifier.py
gym_gathering/wrappers/__init__.py
gym_gathering/wrappers/sample_hard_goals.py
gym_gathering-1.0.4.dist-info/LICENSE
gym_gathering-1.0.4.dist-info/METADATA
gym_gathering-1.0.4.dist-info/WHEEL
gym_gathering-1.0.4.dist-info/top_level.txt
gym_gathering-1.0.4.dist-info/RECORD
