Metadata-Version: 2.1
Name: gym-gathering
Version: 1.0.4
Summary: A gym-compatible reinforcement learning environment which simulates various particle gathering problems
Home-page: https://github.com/NeoExtended/gym-gathering
Author: Matthias Konitzny
Author-email: konitzny@ibr.cs.tu-bs.de
License: MIT
Keywords: reinforcement-learning machine-learning gym environment python data-science particle-gathering gathering particles algorithms
Classifier: Programming Language :: Python :: 3
Classifier: Programming Language :: Python :: 3.7
Classifier: Programming Language :: Python :: 3.8
Classifier: Programming Language :: Python :: 3.9
Classifier: Programming Language :: Python :: 3.10
Requires-Python: >=3.7
License-File: LICENSE
Requires-Dist: gym
Requires-Dist: numpy
Requires-Dist: scipy
Requires-Dist: opencv-python
Provides-Extra: keyboard
Requires-Dist: keyboard ; extra == 'keyboard'
